{"source":"Statistics Canada, 2021 Census of Population, table 98-10-0040 (structural type of dwelling)","sourceUrl":"https://www150.statcan.gc.ca/t1/tbl1/en/tv.action?pid=9810004001","censusYears":["2021"],"typeLabels":{"2021":["Single-detached house","Semi-detached house","Row house","Apartment or flat in a duplex","Apartment in a building that has fewer than five storeys","Apartment in a building that has five or more storeys","Other single-attached house","Movable dwelling"]},"areas":[{"uid":"CA","name":"Canada","level":"country","prov":"CA","census":{"2021":{"total":14978940,"types":[7872310,746560,980105,821490,2738020,1596155,34880,189420]}}},{"uid":"10","name":"Newfoundland and Labrador","level":"province","prov":"10","census":{"2021":{"total":223250,"types":[161410,8695,10770,27535,12330,810,410,1295]}}},{"uid":"11","name":"Prince Edward Island","level":"province","prov":"11","census":{"2021":{"total":64570,"types":[43855,3645,2680,1135,10370,130,85,2680]}}},{"uid":"12","name":"Nova Scotia","level":"province","prov":"12","census":{"2021":{"total":428230,"types":[272980,21605,11220,13165,64575,28645,700,15345]}}},{"uid":"13","name":"New Brunswick","level":"province","prov":"13","census":{"2021":{"total":337655,"types":[228950,13490,9740,13890,51985,4260,1140,14195]}}},{"uid":"24","name":"Quebec","level":"province","prov":"24","census":{"2021":{"total":3749035,"types":[1671920,199080,98625,271245,1242910,225745,15745,23760]}}},{"uid":"35","name":"Ontario","level":"province","prov":"35","census":{"2021":{"total":5491200,"types":[2942995,303260,505265,181030,548785,984665,10220,14985]}}},{"uid":"46","name":"Manitoba","level":"province","prov":"46","census":{"2021":{"total":518055,"types":[343990,18185,19720,7445,74865,43665,600,9590]}}},{"uid":"47","name":"Saskatchewan","level":"province","prov":"47","census":{"2021":{"total":449580,"types":[322070,13680,19860,11240,61855,11040,755,9090]}}},{"uid":"48","name":"Alberta","level":"province","prov":"48","census":{"2021":{"total":1633220,"types":[994565,98740,127735,43730,247030,74880,1220,45325]}}},{"uid":"59","name":"British Columbia","level":"province","prov":"59","census":{"2021":{"total":2041835,"types":[866340,62890,168590,249835,417475,221845,3760,51100]}}},{"uid":"602","name":"Winnipeg (CMA)","level":"cma","prov":"46","census":{"2021":{"total":330325,"types":[199120,12395,12290,5600,57665,41295,310,1655]}}},{"uid":"610","name":"Brandon (CA)","level":"cma","prov":"46","census":{"2021":{"total":22285,"types":[12075,915,1600,530,5220,725,35,1190]}}},{"uid":"607","name":"Portage la Prairie (CA)","level":"cma","prov":"46","census":{"2021":{"total":5640,"types":[3970,145,345,45,800,260,5,85]}}},{"uid":"605","name":"Steinbach (CA)","level":"cma","prov":"46","census":{"2021":{"total":6835,"types":[3755,625,295,260,1490,250,10,160]}}},{"uid":"640","name":"Thompson (CA)","level":"cma","prov":"46","census":{"2021":{"total":4675,"types":[2300,165,440,5,1180,150,5,435]}}},{"uid":"603","name":"Winkler (CA)","level":"cma","prov":"46","census":{"2021":{"total":11365,"types":[7940,690,1030,55,845,355,5,440]}}},{"uid":"705","name":"Regina (CMA)","level":"cma","prov":"47","census":{"2021":{"total":100210,"types":[65495,2710,6190,2215,18660,4390,40,495]}}},{"uid":"725","name":"Saskatoon (CMA)","level":"cma","prov":"47","census":{"2021":{"total":125100,"types":[73660,4605,8255,6800,26060,4725,55,945]}}},{"uid":"750","name":"Estevan (CA)","level":"cma","prov":"47","census":{"2021":{"total":5340,"types":[3680,160,160,75,935,45,10,280]}}},{"uid":"715","name":"Moose Jaw (CA)","level":"cma","prov":"47","census":{"2021":{"total":15215,"types":[10755,430,440,355,2250,635,75,270]}}},{"uid":"735","name":"North Battleford (CA)","level":"cma","prov":"47","census":{"2021":{"total":7865,"types":[5625,265,250,110,1195,150,35,235]}}},{"uid":"745","name":"Prince Albert (CA)","level":"cma","prov":"47","census":{"2021":{"total":17060,"types":[11740,485,495,310,3145,620,10,255]}}},{"uid":"720","name":"Swift Current (CA)","level":"cma","prov":"47","census":{"2021":{"total":7950,"types":[5360,395,365,165,1285,105,10,270]}}},{"uid":"755","name":"Weyburn (CA)","level":"cma","prov":"47","census":{"2021":{"total":5090,"types":[3475,140,105,50,1060,115,5,135]}}},{"uid":"710","name":"Yorkton (CA)","level":"cma","prov":"47","census":{"2021":{"total":8420,"types":[6310,280,230,60,1345,null,null,195]}}}]}
